{"qAprt3eAblgwkJJoD9tBzw==":"photo%20fix%20thing-600x423.jpg","L4oycHXkEfZY3Hp5dVQsjg==":"company%20logo-600x600.jpg","UmubMv1hAnDVegvw3KCnnA==":"company%20logo2-600x423.jpg","H3WPYcsgMnY/y0gVM1pcsQ==":"signature-2-103x128-89-103x128-103x128.png","HznigMHwyrwr1VBNQQbtGQ==":"img-600x400.jpg","d9bOdbAJR/9t+6ioJdepOA==":"photograph%20katana-600x423.jpg","t3VWL+88zqoXzgzDuXRjWw==":"innovate%20contest%20reinaldo%20pedraza-2000x1454.jpg","1v0k+y6GJwhMWSBBs3/BPg==":"innovate%20piece-2000x1125.jpg","aH+ZYSgFQp0eCdiI6J3P+g==":"flower-600x337.jpg","chhX3bFFKkLCLAvAF7E9bw==":"flower-600x423.jpg","JfcCdtY7p9A9TabXmzOb7Q==":"reinaldo%20pedraza%20google%20doodle-2000x800.jpg","pBAhjw5hmiS5AqPdGNqeIQ==":"reinaldo%20pedraza%20banner%205-2000x400.jpg","uQ7gqkh6TNszG8kewoZSMA==":"reinaldo%20pedraza%20wynwood-2000x2962.jpg","6MtVC51cD1Pa99hTUgHfLw==":"reinaldo%20pedraza%20poster%20panel-2000x2666.jpg","muj1EqL9owBXUk89HXiT9g==":"reinaldo%20pedraza%20postcard%20front-2000x1333.jpg","GHmIiQlliQI3TQDw63CrFw==":"company%20logo-2000x2000.jpg","yKBKFsYXG+SzUg46Q+O6nQ==":"img-2000x1333.jpg","YcLiinZp4OzFbQzm9WvvIQ==":"img-1-2000x1333.jpg","M//xQ20vV01/IlsM3W4K9w==":"illustrator%20certification-2000x1542.jpg","g7Q8jB2FAU+cusTg9wCNGA==":"signature-2-103x128-265x329.png","Hp6THZY5MCRQRAxitovPCw==":"photo%20retouching%20for%20website-2000x1125.jpg","EoZi1/bK+KkkNGxlcFeLSQ==":"company%20logo2-2000x1411.jpg","GIHMkrw5mwJ7s+04TbRm4w==":"company%20logo-2000x1125.jpg","KPTl7JSPIugtsGtdEzFAWg==":"master%20image%20jonathon%20corrales%20justin%20gonzalez%20reinaldo%20pedraza-2000x2000.jpg","Xvo3yDdALeXviDc9OntCIA==":"google%20doodle%20for%20web-2000x1125.jpg","SggUAMPrB9q8cIDgfwGMdQ==":"web%20poster%20panel-2000x2962.jpg","jlfdNr1qIbkFGJEGMWKKoQ==":"postcard%20for%20web-2000x1125.jpg","a7WWlOpPO8aNOmJpGN5krg==":"banner%20for%20web-2000x1125.jpg","+XlA2UUS+30ZDrgPoMZlYA==":"img-2-2000x1333.jpg","tKiDAt1toa7PXgawGgFDtA==":"black%20and%20white%20landing%20page-2000x1333.jpg","ggC+ppPqPU7VMBO12KOPOg==":"signature-2-103x128-128x159.png","uWpZCvuKniPTYYHZhSVxfg==":"img-3-2000x1333.jpg","BTC1J5ZFXDCf2ger3oot5A==":"img-2000x3000.jpg","BJtcaeIlo6oGP/5xyC5YXg==":"img-4-2000x1333.jpg","5B2P5Byz+8g55DdIOMVW/Q==":"img-5-2000x1333.jpg","9o0fv2anhHYCSzFyEyMOlQ==":"img-6-2000x1333.jpg","m0rOF/81c83J9+vDntg3Dw==":"img-7-2000x1333.jpg","MeTNJhewsSoz9XDjO6hoQw==":"photograph%20katana-2000x1411.jpg","kFfwKSsHqmAN52tISrKr4A==":"mbr-2000x1333.jpg","q/XK6lwUxyr+6AitqCE7uw==":"flower-2000x1411.jpg","YuwdcYEHzmm9mnMtYDpTAg==":"flower%20fix-2000x1333.jpg","/WUnzis//f+GMNqIvUJX9A==":"art%20piece%201-2000x2400.png","j1El50zKu0RCGW58lhSpdw==":"art%20piece%202-2000x2400.png","2RNTIE9GCkLUl4eyWuhmeA==":"art%20piece%203-2000x2400.png","4cUQODPNtkIUhpcia+s9ZQ==":"art%20piece%204-2000x2400.png","HmMURdnh5SQ7SjmYdg9ucQ==":"art%20piece%205-2000x2400.png","kgC9G4LNPWf98KIk5A7gJQ==":"art%20piece%206-2000x2400.png","Z3o6m80LAT0zD9NyoiFHKA==":"art%20piece%207-2000x2400.png","NQYj0J8F+hlYAG/3k/dt8A==":"art%20piece%208-2000x2400.png","eo9lVXaKmyaA8fupyiBwYw==":"thumbnail-1400x787.jpg","P3kJVFPL3bSCMFv5y7uXKA==":"face%20shatter-2000x1333.jpg"}